pytrack_sent/__init__.py
pytrack_sent/pytrack_types.py
pytrack_sent/tracker.py
pytrack_sent-0.2.5.dist-info/licenses/LICENSE
pytrack_sent-0.2.5.dist-info/METADATA
pytrack_sent-0.2.5.dist-info/WHEEL
pytrack_sent-0.2.5.dist-info/top_level.txt
pytrack_sent-0.2.5.dist-info/RECORD
