Metadata-Version: 2.4
Name: pytrack-sent
Version: 0.2.5
Summary: Lightweight Python performance & event tracker
Home-page: https://github.com/sentinel69402/Pytrack
Author: sentinel
Author-email: sentinelffx@gmail.com
Classifier: Programming Language :: Python :: 3
Classifier: License :: OSI Approved :: MIT License
Classifier: Operating System :: OS Independent
Requires-Python: >=3.10
License-File: LICENSE
Requires-Dist: typing-extensions; python_version < "3.10"
Dynamic: license-file
